neverland_tools/__init__.py
neverland_tools/__pycache__/__init__.cpython-310.pyc
neverland_tools/__pycache__/compile.cpython-310.pyc
neverland_tools/compiler/compile.py
neverland_tools/compiler/__pycache__/compile.cpython-310.pyc
neverland_tools/compiler/__pycache__/release.cpython-310.pyc
neverland_tools-0.1.dev7.dist-info/LICENSE
neverland_tools-0.1.dev7.dist-info/METADATA
neverland_tools-0.1.dev7.dist-info/WHEEL
neverland_tools-0.1.dev7.dist-info/entry_points.txt
neverland_tools-0.1.dev7.dist-info/top_level.txt
neverland_tools-0.1.dev7.dist-info/RECORD
