Metadata-Version: 2.1
Name: neverland-tools
Version: 0.1.dev7
Summary: A tool to compile Python files to shared objects using Cython.
Author-email: umaru <15875339926@139.com>
License: MIT
Project-URL: Homepage, https://github.com/NeverlandLab/neverland-tools
Classifier: Programming Language :: Python :: 3
Classifier: License :: OSI Approved :: MIT License
Classifier: Operating System :: OS Independent
Requires-Python: >=3.10
License-File: LICENSE
Provides-Extra: compile
Requires-Dist: Cython==3.0.11; extra == "compile"
Provides-Extra: dev
Requires-Dist: twine; extra == "dev"
